social_auth_storage_mongoengine-1.0.1.dist-info/DESCRIPTION.rst
social_auth_storage_mongoengine-1.0.1.dist-info/METADATA
social_auth_storage_mongoengine-1.0.1.dist-info/RECORD
social_auth_storage_mongoengine-1.0.1.dist-info/WHEEL
social_auth_storage_mongoengine-1.0.1.dist-info/metadata.json
social_auth_storage_mongoengine-1.0.1.dist-info/top_level.txt
social_mongoengine/__init__.py
social_mongoengine/storage.py
