Metadata-Version: 1.1
Name: social-auth-storage-mongoengine
Version: 1.0.1
Summary: Python Social Authentication, Mongoengine storage.
Home-page: https://github.com/python-social-auth/social-storage-mongoengine
Author: Matias Aguirre
Author-email: matiasaguirre@gmail.com
License: BSD
Keywords: mongoengine,social auth
Platform: UNKNOWN
Classifier: Development Status :: 4 - Beta
Classifier: Topic :: Internet
Classifier: License :: OSI Approved :: BSD License
Classifier: Intended Audience :: Developers
Classifier: Environment :: Web Environment
Classifier: Programming Language :: Python
Classifier: Programming Language :: Python :: 2.7
Classifier: Programming Language :: Python :: 3
